[
  {
    "name":"Deccan RubyConf",
    "url":"http://www.deccanrubyconf.org/",
    "date":"Aug 12, 2017",
    "city":"Pune",
    "country":" India",
    "twitter":"https://twitter.com/deccanrubyconf"
  },
  {
    "name":"RubyConf Colombia",
    "url":"http://www.rubyconf.co/",
    "date":"September 8-9, 2017",
    "city":"Medellin",
    "country":" Colombia",
    "twitter":"https://twitter.com/rubyconfco"
  },
  {
    "name":"RubyConf China",
    "url":"http://rubyconfchina.org/",
    "date":"September 16-17, 2017",
    "city":"Hangzhou",
    "country":" China"
  },
  {
    "name":"RubyKaigi",
    "url":"http://rubykaigi.org/2017",
    "date":"September 18-20, 2017",
    "city":"Hiroshima",
    "country":" Japan",
    "twitter":"https://twitter.com/rubykaigi"
  },
  {
    "name":"RailsClub",
    "url":"http://railsclub.ru/en/main",
    "date":"September 23, 2017",
    "city":"Moscow",
    "country":" Russia",
    "twitter":"https://twitter.com/railsclub_ru"
  },
  {
    "name":"EuRuKo",
    "url":"http://www.euruko2017.org/",
    "date":"September 29-30, 2017",
    "city":"Budapest",
    "country":" Hungary",
    "twitter":"https://twitter.com/euruko"
  },
  {
    "name":"Southeast Ruby",
    "url":"https://southeastruby.com/",
    "date":"October 5-6, 2017",
    "city":"Nashville",
    "country":" TN",
    "twitter":"https://twitter.com/southeastruby"
  },
  {
    "name":"RubyConf Jakarta",
    "url":"http://ruby.id/conf/2017/",
    "date":"October 6-7, 2017",
    "city":"Jakarta",
    "country":" Indonesia",
    "twitter":"https://twitter.com/id_ruby"
  },
  {
    "name":"RubyConf MY",
    "url":"http://rubyconf.my/",
    "date":"October 12-13, 2017",
    "city":"Cyberjaya",
    "country":" Malaysia",
    "twitter":"https://twitter.com/rubyconfmy"
  },
  {
    "name":"Keep Ruby Weird",
    "url":"https://keeprubyweird.com/",
    "date":"October 27, 2017",
    "city":"Austin",
    "country":" Texas",
    "twitter":"https://twitter.com/keeprubyweird"
  },
  {
    "name":"RubyWorld Conference",
    "url":"http://2016.rubyworld-conf.org/en/news/2017/01/rwc2017/",
    "date":"November 1-2, 2017",
    "city":"Matsue,  Shimane",
    "country":" Japan",
    "twitter":"https://twitter.com/rubyworldconf"
  },
  {
    "name":"Kiwi Ruby",
    "url":"http://kiwi.ruby.nz/",
    "date":"November 2-3, 2017",
    "city":"Wellington",
    "country":" New Zealand",
    "twitter":"https://twitter.com/kiwirubyconf"
  },
  {
    "name":"RubyConf",
    "url":"http://rubyconf.org/",
    "date":"November 15-17th, 2017",
    "city":"New Orleans",
    "country":" LA",
    "twitter":"https://twitter.com/rubyconf"
  },
  {
    "name":"RailsIsrael",
    "url":"",
    "date":"November 28-30, 2017",
    "city":"Tel Aviv",
    "country":" Israel",
    "twitter":"https://twitter.com/fogelmania"
  },
  {
    "name":"Ruby on Ice",
    "url":"https://rubyonice.com/",
    "date":"January 26-28th, 2018",
    "city":"Tegernsee",
    "country":" Germany",
    "twitter":"https://twitter.com/rubyoniceconf"
  },
  {
    "name":"Bath Ruby Conference",
    "url":"http://2018.bathruby.uk/",
    "date":"March 22-23, 2018",
    "city":"Bath",
    "country":" UK",
    "twitter":"https://twitter.com/bathruby"
  }
]
